celsus/__init__.py
celsus/logger/__init__.py
celsus/logger/logger.py
celsus/toolbox/__init__.py
celsus/toolbox/email_sender.py
celsus/toolbox/pandas.py
celsus/toolbox/service_errors.py
celsus/toolbox/statistical.py
celsus_colendi-0.0.6.dist-info/METADATA
celsus_colendi-0.0.6.dist-info/WHEEL
celsus_colendi-0.0.6.dist-info/top_level.txt
celsus_colendi-0.0.6.dist-info/RECORD
