Metadata-Version: 2.1
Name: celsus-colendi
Version: 0.0.6
Summary: Colendi data team package
Home-page: http://gitlab.colendi.com/data-team/data_package.git
Author: Caner Taş
Author-email: <caner.tas@colendi.com>
Keywords: python
Classifier: Development Status :: 3 - Alpha
Classifier: Intended Audience :: Education
Classifier: Programming Language :: Python :: 2
Classifier: Programming Language :: Python :: 3
Classifier: Operating System :: MacOS :: MacOS X
Classifier: Operating System :: Microsoft :: Windows
Requires-Dist: Werkzeug
Requires-Dist: setuptools
Requires-Dist: pandas
Requires-Dist: datetime
